{
    "dataset": "pfs_pfin_termometro",
    "table": "etl_trans_adesao_flex_multiplo",
    "schema": [
        {
            "name": "dat_transacao",
            "type": "TIMESTAMP",
            "mode": "NULLABLE"
        },
        {
            "name": "id_eventotransacao",
            "type": "STRING",
            "mode": "NULLABLE"
        },
        {
            "name": "cod_status_transacao",
            "type": "INTEGER",
            "mode": "NULLABLE"
        },
        {
            "name": "des_status_transacao",
            "type": "STRING",
            "mode": "NULLABLE"
        },
        {
            "name": "id_transacao",
            "type": "STRING",
            "mode": "NULLABLE"
        },
        {
            "name": "des_transacao",
            "type": "STRING",
            "mode": "NULLABLE"
        },
        {
            "name": "num_cpf",
            "type": "INTEGER",
            "mode": "NULLABLE"
        },
        {
            "name": "cod_estabelecimento",
            "type": "INTEGER",
            "mode": "NULLABLE"
        },
        {
            "name": "val_transacao",
            "type": "STRING",
            "mode": "NULLABLE"
        },
        {
            "name": "id_conta",
            "type": "INTEGER",
            "mode": "NULLABLE"
        },
        {
            "name": "id_cartao",
            "type": "STRING",
            "mode": "NULLABLE"
        },
        {
            "name": "cod_cartao",
            "type": "STRING",
            "mode": "NULLABLE"
        },
        {
            "name": "ind_titular",
            "type": "INTEGER",
            "mode": "NULLABLE"
        },
        {
            "name": "id_produto",
            "type": "INTEGER",
            "mode": "NULLABLE"
        },
        {
            "name": "dat_adesao_conta",
            "type": "TIMESTAMP",
            "mode": "NULLABLE"
        },
        {
            "name": "dat_emissao_cartao",
            "type": "TIMESTAMP",
            "mode": "NULLABLE"
        },
        {
            "name": "cod_prod_financeiro",
            "type": "INTEGER",
            "mode": "NULLABLE"
        },
        {
            "name": "num_chapa_vendedor",
            "type": "STRING",
            "mode": "NULLABLE"
        },
        {
            "name": "dat_ult_atu",
            "type": "TIMESTAMP",
            "mode": "NULLABLE"
        },
        {
            "name": "des_canal",
            "type": "STRING",
            "mode": "NULLABLE"
        },
        {
            "name": "qtde_parcelas",
            "type": "STRING",
            "mode": "NULLABLE"
        }
    ]
}