{
    "dataset": "pfs_raw_conductor",
    "table": "seguro_parcela",
    "schema": [
        {
            "name": "hash_key",
            "type": "STRING",
            "mode": "NULLABLE"
        },
        {
            "name": "source",
            "type": "STRING",
            "mode": "NULLABLE"
        },
        {
            "name": "par_id_parcelaseguro",
            "type": "INTEGER",
            "mode": "NULLABLE"
        },
        {
            "name": "par_id_adesaoseguro",
            "type": "INTEGER",
            "mode": "NULLABLE"
        },
        {
            "name": "par_no_parcela",
            "type": "INTEGER",
            "mode": "NULLABLE"
        },
        {
            "name": "par_dt_vencimento",
            "type": "TIMESTAMP",
            "mode": "NULLABLE"
        },
        {
            "name": "par_vl_parcela",
            "type": "FLOAT",
            "mode": "NULLABLE"
        },
        {
            "name": "par_tp_situacao",
            "type": "INTEGER",
            "mode": "NULLABLE"
        },
        {
            "name": "par_dt_situacao",
            "type": "TIMESTAMP",
            "mode": "NULLABLE"
        },
        {
            "name": "par_dt_emissao",
            "type": "TIMESTAMP",
            "mode": "NULLABLE"
        },
        {
            "name": "par_tp_situacaocobranca",
            "type": "INTEGER",
            "mode": "NULLABLE"
        },
        {
            "name": "par_tp_situacaotransferencia",
            "type": "INTEGER",
            "mode": "NULLABLE"
        },
        {
            "name": "par_no_titulocapitalizacao",
            "type": "STRING",
            "mode": "NULLABLE"
        },
        {
            "name": "par_fl_pagamentopdv",
            "type": "BOOLEAN",
            "mode": "NULLABLE"
        },
        {
            "name": "par_dt_enviocobranca",
            "type": "TIMESTAMP",
            "mode": "NULLABLE"
        },
        {
            "name": "par_dt_postagemparcela",
            "type": "TIMESTAMP",
            "mode": "NULLABLE"
        },
        {
            "name": "par_dt_liquidacao",
            "type": "TIMESTAMP",
            "mode": "NULLABLE"
        },
        {
            "name": "par_tp_formapagamento",
            "type": "INTEGER",
            "mode": "NULLABLE"
        },
        {
            "name": "dh_relatorio",
            "type": "TIMESTAMP",
            "mode": "NULLABLE"
        },
        {
            "name": "operation",
            "type": "STRING",
            "mode": "NULLABLE"
        },
        {
            "name": "operation_sequence",
            "type": "INTEGER",
            "mode": "NULLABLE"
        },
        {
            "name": "production_date",
            "type": "DATE",
            "mode": "NULLABLE"
        }
    ]
}